twitchvod/__init__.py
twitchvod/__version__.py
twitchvod/client.py
twitchvod/exceptions.py
twitchvod/models.py
twitchvod/utils.py
twitchvod-0.1.2.data/data/HISTORY.md
twitchvod-0.1.2.data/data/LICENSE
twitchvod-0.1.2.data/data/README.md
twitchvod-0.1.2.dist-info/LICENSE
twitchvod-0.1.2.dist-info/METADATA
twitchvod-0.1.2.dist-info/WHEEL
twitchvod-0.1.2.dist-info/top_level.txt
twitchvod-0.1.2.dist-info/RECORD
