Metadata-Version: 2.1
Name: twitchvod
Version: 0.1.2
Summary: Fetch Twitch VOD MPEG-2 Stream Information
Home-page: https://github.com/nomadmtb/twitchvod
Author: Kyle Luce <nomadmtb>
Author-email: nomadmtb@users.noreply.github.com
License: MIT License
Platform: UNKNOWN
Requires-Python: >=3.5.2
Requires-Dist: requests (<=2.22.0,>=2.13.0)
